<?xml version="1.0" encoding="UTF-8"?>
<gresources>
  <gresource prefix="/dev/lumen/panel">
    <file compressed="true">style.css</file>
  </gresource>
  <gresource prefix="/dev/lumen/panel/icons">
    <file alias="app.svg">res/app.svg</file>
    <file alias="bluetooth.svg">res/bluetooth.svg</file>
    <file alias="bluetooth-connected.svg">res/bluetooth-connected.svg</file>
    <file alias="bluetooth-off.svg">res/bluetooth-off.svg</file>
    <file alias="charging.svg">res/charging.svg</file>
    <file alias="close.svg">res/close.svg</file>
    <file alias="ethernet.svg">res/ethernet.svg</file>
    <file alias="hibernate.svg">res/hibernate.svg</file>
    <file alias="high.svg">res/high.svg</file>
    <file alias="leaving.svg">res/leaving.svg</file>
    <file alias="logout.svg">res/logout.svg</file>
    <file alias="low.svg">res/low.svg</file>
    <file alias="mid.svg">res/mid.svg</file>
    <file alias="nobattery.svg">res/nobattery.svg</file>
    <file alias="nowifi.svg">res/nowifi.svg</file>
    <file alias="reboot.svg">res/reboot.svg</file>
    <file alias="shutdown.svg">res/shutdown.svg</file>
    <file alias="sound-max.svg">res/sound-max.svg</file>
    <file alias="sound-mute.svg">res/sound-mute.svg</file>
    <file alias="suspend.svg">res/suspend.svg</file>
    <file alias="wifi.svg">res/wifi.svg</file>
    <file alias="wifi-unknown.svg">res/wifi-unknown.svg</file>
    <file alias="wired.svg">res/wired.svg</file>
  </gresource>
</gresources>
